awssaml/CLIDriver.py
awssaml/__init__.py
awssaml/__main__.py
awssaml/api/ADFSConnection.py
awssaml/api/ADFSService.py
awssaml/api/Authentication.py
awssaml/api/AwsConfiguration.py
awssaml/api/AwsCredentials.py
awssaml/api/AwsStsService.py
awssaml/api/PasswordDecrypt.py
awssaml/api/__init__.py
awssaml/commands/ApiCommand.py
awssaml/commands/Base.py
awssaml/commands/ConsoleCommand.py
awssaml/commands/__init__.py
awssaml-1.0.0.data/scripts/awssaml
awssaml-1.0.0.dist-info/LICENSE
awssaml-1.0.0.dist-info/METADATA
awssaml-1.0.0.dist-info/WHEEL
awssaml-1.0.0.dist-info/entry_points.txt
awssaml-1.0.0.dist-info/top_level.txt
awssaml-1.0.0.dist-info/RECORD
