Metadata-Version: 2.1
Name: awssaml
Version: 1.0.0
Summary: Security Assertion Markup Language (SAML) for Amazon.
Home-page: https://github.com/jupeter/awssaml
Author: Piotr Plenik
Author-email: piotr.plenik@gmail.com
License: UNKNOWN
Platform: UNKNOWN
Classifier: Development Status :: 4 - Beta
Classifier: Environment :: Console
Classifier: Environment :: Other Environment
Classifier: Intended Audience :: Developers
Classifier: Intended Audience :: Information Technology
Classifier: License :: OSI Approved :: Apache Software License
Classifier: Operating System :: OS Independent
Classifier: Programming Language :: Python
Classifier: Programming Language :: Python :: 3.7
Classifier: Programming Language :: Python :: 2.7
Classifier: Topic :: Internet
Classifier: Topic :: Software Development :: Build Tools
Classifier: Topic :: Utilities
Requires-Dist: docopt (<=0.6.2,>=0.6.0)
Requires-Dist: beautifulsoup4 (<4.8.0,>=4.7.1)
Requires-Dist: requests-ntlm (<1.2.0,>=1.1.0)
Requires-Dist: requests (<2.23.0,>=2.22.0)
Requires-Dist: configparser (<3.8.0,>=3.7.4)
Requires-Dist: boto3 (<1.10.0,>=1.9.184)
Requires-Dist: keyring (<19.3.0,>=18.0.1)
